{
  "lastRun": "2026-02-10T15:57:30.065Z",
  "lastSuccess": "2026-02-10T15:57:37.807Z",
  "lastFailure": "2026-02-10T16:16:04.865Z",
  "errorCount": 932,
  "consecutiveFailures": 12,
  "status": "failed",
  "lastTerminationReason": "mistake_limit_reached",
  "earlyTerminationCount": 11,
  "totalExecutionTimeMs": 52600974,
  "averageExecutionTimeMs": 4383415,
  "successfulTerminations": 0,
  "failedTerminations": 11,
  "error": "Failed to acquire lock for task 'prompt' after 3 attempts: Failed to acquire lock for task 'prompt': timeout after 5000ms"
}